Metadata-Version: 2.1
Name: tsatsubasiccalculator
Version: 0.0.2
Summary: A very basic calculator
Home-page: 
Author: Akorlie Edward Tsatsu
Author-email: edwardakorlie73@gmail.com
License: MIT
Keywords: calculator
Classifier: Development Status :: 5 - Production/Stable
Classifier: Intended Audience :: Education
Classifier: Operating System :: Microsoft :: Windows :: Windows 10
Classifier: License :: OSI Approved :: MIT License
Classifier: Programming Language :: Python :: 3
License-File: LICENCE.txt
